setup.cfg
setup.py
marrow/__init__.py
marrow.util.egg-info/PKG-INFO
marrow.util.egg-info/SOURCES.txt
marrow.util.egg-info/dependency_links.txt
marrow.util.egg-info/namespace_packages.txt
marrow.util.egg-info/top_level.txt
marrow.util.egg-info/zip-safe
marrow/util/__init__.py
marrow/util/bunch.py
marrow/util/compat.py
marrow/util/convert.py
marrow/util/escape.py
marrow/util/events.py
marrow/util/futures.py
marrow/util/insensitive.py
marrow/util/object.py
marrow/util/path.py
marrow/util/patterns.py
marrow/util/pipe.py
marrow/util/release.py
marrow/util/text.py
marrow/util/time.py
marrow/util/tuple.py
marrow/util/url.py
marrow/util/context/__init__.py
marrow/util/context/cwd.py