Metadata-Version: 1.0
Name: marrow.util
Version: 1.2.1
Summary: A collection of many commonly reimplemented utility classes and functions.
Home-page: https://github.com/marrow/marrow.util
Author: Alice Bevan-McGregor
Author-email: alice+marrow@gothcandy.com
License: MIT
Platform: UNKNOWN
Classifier: Development Status :: 5 - Production/Stable
Classifier: Environment :: Console
Classifier: Intended Audience :: Developers
Classifier: License :: OSI Approved :: MIT License
Classifier: Operating System :: OS Independent
Classifier: Programming Language :: Python
Classifier: Programming Language :: Python :: 2.6
Classifier: Programming Language :: Python :: 2.7
Classifier: Programming Language :: Python :: 3
Classifier: Programming Language :: Python :: 3.1
Classifier: Programming Language :: Python :: 3.2
Classifier: Topic :: Software Development :: Libraries :: Python Modules
Classifier: Topic :: Utilities
